datarobot_pulumi_utils/__init__.py
datarobot_pulumi_utils/_version.py
datarobot_pulumi_utils/py.typed
datarobot_pulumi_utils/common/__init__.py
datarobot_pulumi_utils/common/feature_flags.py
datarobot_pulumi_utils/common/urls.py
datarobot_pulumi_utils/pulumi/__init__.py
datarobot_pulumi_utils/pulumi/challenger.py
datarobot_pulumi_utils/pulumi/custom_model_deployment.py
datarobot_pulumi_utils/pulumi/dataset_provider.py
datarobot_pulumi_utils/pulumi/dataset_refresh_provider.py
datarobot_pulumi_utils/pulumi/export_collector.py
datarobot_pulumi_utils/pulumi/papermill.py
datarobot_pulumi_utils/pulumi/playground_custom_model.py
datarobot_pulumi_utils/pulumi/project.py
datarobot_pulumi_utils/pulumi/proxy_llm_blueprint.py
datarobot_pulumi_utils/pulumi/rag_custom_model.py
datarobot_pulumi_utils/pulumi/stack.py
datarobot_pulumi_utils/schema/__init__.py
datarobot_pulumi_utils/schema/apps.py
datarobot_pulumi_utils/schema/base.py
datarobot_pulumi_utils/schema/common.py
datarobot_pulumi_utils/schema/custom_models.py
datarobot_pulumi_utils/schema/data_connections.py
datarobot_pulumi_utils/schema/datasets.py
datarobot_pulumi_utils/schema/exec_envs.py
datarobot_pulumi_utils/schema/guardrails.py
datarobot_pulumi_utils/schema/llms.py
datarobot_pulumi_utils/schema/predictions.py
datarobot_pulumi_utils/schema/training.py
datarobot_pulumi_utils/schema/vectordb.py
datarobot_pulumi_utils-0.1.1.dist-info/METADATA
datarobot_pulumi_utils-0.1.1.dist-info/WHEEL
datarobot_pulumi_utils-0.1.1.dist-info/licenses/AUTHORS
datarobot_pulumi_utils-0.1.1.dist-info/licenses/LICENSE
datarobot_pulumi_utils-0.1.1.dist-info/RECORD
